mesospim_python_tools/__init__.py
mesospim_python_tools/io.py
mesospim_python_tools/metadata.py
mesoSPIM_python_tools-0.0.3.dist-info/LICENSE
mesoSPIM_python_tools-0.0.3.dist-info/METADATA
mesoSPIM_python_tools-0.0.3.dist-info/WHEEL
mesoSPIM_python_tools-0.0.3.dist-info/top_level.txt
mesoSPIM_python_tools-0.0.3.dist-info/RECORD
